exendb/__init__.py
exendb/datamodels.py
exendb/enums.py
exendb/exceptions.py
exendb/utils.py
exendb-0.0.2.dist-info/LICENSE
exendb-0.0.2.dist-info/METADATA
exendb-0.0.2.dist-info/WHEEL
exendb-0.0.2.dist-info/top_level.txt
exendb-0.0.2.dist-info/RECORD
