Metadata-Version: 2.1
Name: exendb
Version: 0.0.2
Summary: A simple library that covers sqlite3's basic functionality.
Home-page: https://github.com/Exenifix/ExenDB
Author: Exenifix
License: MIT
Platform: UNKNOWN
Classifier: Programming Language :: Python :: 3
Classifier: License :: OSI Approved :: MIT License
Classifier: Operating System :: OS Independent
Requires-Python: >=3.7
License-File: LICENSE
